docx_charts/__init__.py
docx_charts/chart.py
docx_charts/document.py
docx_charts-0.1.12.dist-info/LICENSE
docx_charts-0.1.12.dist-info/METADATA
docx_charts-0.1.12.dist-info/WHEEL
docx_charts-0.1.12.dist-info/RECORD
