Metadata-Version: 2.1
Name: docx-charts
Version: 0.1.12
Summary: Python library for manipulating chart data in word documents
Author: Julia van der Kris
Author-email: julia@juuuuuuuuuuuuuuuuuuuuuuuuuuuuuuuuuuuuuuuuuuuuuuuuuuuuuuuuuuulia.dev
Requires-Python: >=3.11,<4.0
Classifier: Programming Language :: Python :: 3
Classifier: Programming Language :: Python :: 3.11
